pydelorean/__init__.py
pydelorean/delorean.py
pydelorean/errors.py
pydelorean/files.py
pydelorean/base/__init__.py
pydelorean/base/forest.py
pydelorean/base/node.py
pydelorean/parser/__init__.py
pydelorean/parser/parser.py
pydelorean/parser/utils.py
pydelorean/tools/__init__.py
pydelorean-1.5.4.dist-info/LICENSE
pydelorean-1.5.4.dist-info/METADATA
pydelorean-1.5.4.dist-info/WHEEL
pydelorean-1.5.4.dist-info/top_level.txt
pydelorean-1.5.4.dist-info/RECORD
