Metadata-Version: 2.1
Name: pydelorean
Version: 1.5.4
Summary: A package to convert between markup documents and a forest data structure for efficient processing.
Home-page: http://github.com/kj3moraes/delorean
Author: Keane Moraes
Author-email: lordvader3002@gmail.com
License: Apache 2.0
Download-URL: https://github.com/kj3moraes/delorean/archive/1.5.4.zip
Platform: UNKNOWN
Classifier: Topic :: Utilities
License-File: LICENSE
Requires-Dist: beautifulsoup4
Requires-Dist: bigtree
Requires-Dist: markdown
